napari_live_recording/__init__.py
napari_live_recording/_version.py
napari_live_recording/napari.yaml
napari_live_recording/_test/conftest.py
napari_live_recording/_test/test_recording.py
napari_live_recording/_test/test_settings.py
napari_live_recording/_test/test_ui.py
napari_live_recording/common/__init__.py
napari_live_recording/control/__init__.py
napari_live_recording/control/frame_buffer.py
napari_live_recording/control/devices/__init__.py
napari_live_recording/control/devices/interface.py
napari_live_recording/control/devices/micro_manager.py
napari_live_recording/control/devices/opencv.py
napari_live_recording/control/devices/pymicroscope.py
napari_live_recording/processing_engine/__init__.py
napari_live_recording/processing_engine/processing_gui.py
napari_live_recording/processing_engine/testImage.jpg
napari_live_recording/processing_engine/image_filters/__init__.py
napari_live_recording/ui/__init__.py
napari_live_recording/ui/widgets.py
napari_live_recording-0.3.8.dist-info/LICENSE
napari_live_recording-0.3.8.dist-info/METADATA
napari_live_recording-0.3.8.dist-info/WHEEL
napari_live_recording-0.3.8.dist-info/entry_points.txt
napari_live_recording-0.3.8.dist-info/top_level.txt
napari_live_recording-0.3.8.dist-info/RECORD
