Metadata-Version: 2.1
Name: napari-live-recording
Version: 0.3.8
Summary: A napari plugin for live video recording with a generic camera device.
Home-page: https://github.com/jethro33/napari-live-recording
Author: "Jacopo Abramo, Pia Pritzke, Felix Wanitschke"
Author-email: jacopo.abramo@gmail.com
License: MIT
Project-URL: Bug Tracker, https://github.com/jacopoabramo/napari-live-recording/issues
Project-URL: Documentation, https://github.com/jacopoabramo/napari-live-recording#README.md
Project-URL: Source Code, https://github.com/jacopoabramo/napari-live-recording
Project-URL: User Support, https://github.com/jacopoabramo/napari-live-recording/issues
Classifier: Development Status :: 4 - Beta
Classifier: Intended Audience :: Developers
Classifier: Intended Audience :: Science/Research
Classifier: Intended Audience :: Education
Classifier: Framework :: napari
Classifier: Programming Language :: Python
Classifier: Programming Language :: Python :: 3
Classifier: Programming Language :: Python :: 3.9
Classifier: Programming Language :: Python :: 3.10
Classifier: Programming Language :: Python :: 3.11
Classifier: Operating System :: OS Independent
Classifier: License :: OSI Approved :: MIT License
Classifier: Topic :: Scientific/Engineering :: Image Processing
Classifier: Topic :: Scientific/Engineering :: Visualization
Requires-Python: >=3.9
License-File: LICENSE
Requires-Dist: superqt
Requires-Dist: numpy
Requires-Dist: opencv-python
Requires-Dist: tifffile
Requires-Dist: napari[all]
Requires-Dist: qtpy
Requires-Dist: microscope >=0.7.0
Requires-Dist: pims
Requires-Dist: pyqtgraph
Requires-Dist: pymmcore-plus >=0.6.7
Requires-Dist: pymmcore-widgets
Provides-Extra: testing
Requires-Dist: tox ; extra == 'testing'
Requires-Dist: pytest ; extra == 'testing'
Requires-Dist: pytest-cov ; extra == 'testing'
Requires-Dist: pytest-qt ; extra == 'testing'
Requires-Dist: napari ; extra == 'testing'
Requires-Dist: pyqt5 ; extra == 'testing'
